README.md
setup.py
microbus/__init__.py
microbus/assignment.py
microbus/bus.py
microbus/route.py
microbus/scheduler.py
microbus/scheduler_disjoint.py
microbus/stop.py
microbus/test_assignment.py
microbus/test_bus.py
microbus/test_route.py
microbus/test_scheduler.py
microbus/test_scheduler_disjoint.py
microbus/test_stop.py
microbus.egg-info/PKG-INFO
microbus.egg-info/SOURCES.txt
microbus.egg-info/dependency_links.txt
microbus.egg-info/requires.txt
microbus.egg-info/top_level.txt