Metadata-Version: 1.1
Name: microbus
Version: 0.2.0
Summary:  A simple detached data carrying mechanism across different stages of a pipeline design or similar 
Home-page: http://github.com/tgalal/microbus
Author: Tarek Galal
Author-email: tare2.galal@gmail.com
License: MIT
Platform: any
Classifier: Programming Language :: Python
Classifier: Development Status :: 4 - Beta
Classifier: Natural Language :: English
Classifier: Intended Audience :: Developers
Classifier: License :: OSI Approved :: MIT License
Classifier: Operating System :: OS Independent
Classifier: Topic :: Software Development :: Libraries :: Python Modules
